{
  "generatedAt": "2026-04-12",
  "accountId": 147318014,
  "period": "2026-04-01 to 2026-04-30",
  "filter": "Number of plants is known; Create Date in April 2026",
  "plantBuckets": [
    "Less than 15",
    "15-30",
    "30-100",
    "More than 100"
  ],
  "columnTotals": {
    "Less than 15": 138,
    "15-30": 30,
    "30-100": 11,
    "More than 100": 4
  },
  "grandTotal": 183,
  "rows": [
    {
      "utm_content": "(no utm_content)",
      "total": 85,
      "totalPct": 46.4,
      "Less than 15": 55,
      "15-30": 20,
      "30-100": 7,
      "More than 100": 3,
      "Less than 15 %": 39.9,
      "15-30 %": 66.7,
      "30-100 %": 63.6,
      "More than 100 %": 75.0
    },
    {
      "utm_content": "prospecting_web_lal-existing-customers-conv_b2bconv-ADV[12.3.2026]",
      "total": 36,
      "totalPct": 19.7,
      "Less than 15": 30,
      "15-30": 4,
      "30-100": 2,
      "More than 100": 0,
      "Less than 15 %": 21.7,
      "15-30 %": 13.3,
      "30-100 %": 18.2,
      "More than 100 %": 0.0
    },
    {
      "utm_content": "prospecting_web__lal-b2b-conv_b2bconv[24.2.26]",
      "total": 16,
      "totalPct": 8.7,
      "Less than 15": 15,
      "15-30": 1,
      "30-100": 0,
      "More than 100": 0,
      "Less than 15 %": 10.9,
      "15-30 %": 3.3,
      "30-100 %": 0.0,
      "More than 100 %": 0.0
    },
    {
      "utm_content": "prospecting_web__lal-existing-customers-conv_b2bconv[2.3.26]",
      "total": 11,
      "totalPct": 6.0,
      "Less than 15": 9,
      "15-30": 1,
      "30-100": 1,
      "More than 100": 0,
      "Less than 15 %": 6.5,
      "15-30 %": 3.3,
      "30-100 %": 9.1,
      "More than 100 %": 0.0
    },
    {
      "utm_content": "prospecting_web_broad_broad_auto_BusinessAngles-UK-Offices-Joel-b2bconv[5.1.26]",
      "total": 10,
      "totalPct": 5.5,
      "Less than 15": 8,
      "15-30": 2,
      "30-100": 0,
      "More than 100": 0,
      "Less than 15 %": 5.8,
      "15-30 %": 6.7,
      "30-100 %": 0.0,
      "More than 100 %": 0.0
    },
    {
      "utm_content": "prospecting_web_lal-b2b-conv_b2bconv_UK[10.3.2026]",
      "total": 7,
      "totalPct": 3.8,
      "Less than 15": 5,
      "15-30": 2,
      "30-100": 0,
      "More than 100": 0,
      "Less than 15 %": 3.6,
      "15-30 %": 6.7,
      "30-100 %": 0.0,
      "More than 100 %": 0.0
    },
    {
      "utm_content": "prospecting_web_lal-existing-customers-conv_b2bconv-RVR[23.3.26]",
      "total": 5,
      "totalPct": 2.7,
      "Less than 15": 5,
      "15-30": 0,
      "30-100": 0,
      "More than 100": 0,
      "Less than 15 %": 3.6,
      "15-30 %": 0.0,
      "30-100 %": 0.0,
      "More than 100 %": 0.0
    },
    {
      "utm_content": "Easyplant",
      "total": 4,
      "totalPct": 2.2,
      "Less than 15": 4,
      "15-30": 0,
      "30-100": 0,
      "More than 100": 0,
      "Less than 15 %": 2.9,
      "15-30 %": 0.0,
      "30-100 %": 0.0,
      "More than 100 %": 0.0
    },
    {
      "utm_content": "{{adset.name}}",
      "total": 3,
      "totalPct": 1.6,
      "Less than 15": 2,
      "15-30": 0,
      "30-100": 0,
      "More than 100": 1,
      "Less than 15 %": 1.4,
      "15-30 %": 0.0,
      "30-100 %": 0.0,
      "More than 100 %": 25.0
    },
    {
      "utm_content": "test_content",
      "total": 1,
      "totalPct": 0.5,
      "Less than 15": 1,
      "15-30": 0,
      "30-100": 0,
      "More than 100": 0,
      "Less than 15 %": 0.7,
      "15-30 %": 0.0,
      "30-100 %": 0.0,
      "More than 100 %": 0.0
    },
    {
      "utm_content": "Self_Water_Planters",
      "total": 1,
      "totalPct": 0.5,
      "Less than 15": 1,
      "15-30": 0,
      "30-100": 0,
      "More than 100": 0,
      "Less than 15 %": 0.7,
      "15-30 %": 0.0,
      "30-100 %": 0.0,
      "More than 100 %": 0.0
    },
    {
      "utm_content": "prospecting_web_broad_broad_auto_WateringSequence-Take2[7.3.26]",
      "total": 1,
      "totalPct": 0.5,
      "Less than 15": 1,
      "15-30": 0,
      "30-100": 0,
      "More than 100": 0,
      "Less than 15 %": 0.7,
      "15-30 %": 0.0,
      "30-100 %": 0.0,
      "More than 100 %": 0.0
    },
    {
      "utm_content": "prospecting_web_broad_broad_auto_SalVO-MentalPet-Ofer[4.10.2025]",
      "total": 1,
      "totalPct": 0.5,
      "Less than 15": 1,
      "15-30": 0,
      "30-100": 0,
      "More than 100": 0,
      "Less than 15 %": 0.7,
      "15-30 %": 0.0,
      "30-100 %": 0.0,
      "More than 100 %": 0.0
    },
    {
      "utm_content": "Office_Plants",
      "total": 1,
      "totalPct": 0.5,
      "Less than 15": 1,
      "15-30": 0,
      "30-100": 0,
      "More than 100": 0,
      "Less than 15 %": 0.7,
      "15-30 %": 0.0,
      "30-100 %": 0.0,
      "More than 100 %": 0.0
    },
    {
      "utm_content": "NearMe_Store",
      "total": 1,
      "totalPct": 0.5,
      "Less than 15": 0,
      "15-30": 0,
      "30-100": 1,
      "More than 100": 0,
      "Less than 15 %": 0.0,
      "15-30 %": 0.0,
      "30-100 %": 9.1,
      "More than 100 %": 0.0
    }
  ]
}